mst/tdx/__init__.py
mst/tdx/tdx.py
mst_tdx-1.0.8.dist-info/METADATA
mst_tdx-1.0.8.dist-info/WHEEL
mst_tdx-1.0.8.dist-info/top_level.txt
mst_tdx-1.0.8.dist-info/RECORD
