Metadata-Version: 2.4
Name: mst-tdx
Version: 1.0.8
Summary: An interface for TeamDynamix
Author-email: Missouri University of Science and Technology - Information Technology <it-ai@mst.edu>
Requires-Python: >=3.11
Requires-Dist: mst-core
Requires-Dist: mst-authsrv
Requires-Dist: requests
